LICENSE
README.rst
setup.py
enstop/__init__.py
enstop/block_parallel_plsa.py
enstop/cuda_plsa.py
enstop/distributed_plsa.py
enstop/enstop_.py
enstop/plsa.py
enstop/streamed_plsa.py
enstop/utils.py
enstop.egg-info/PKG-INFO
enstop.egg-info/SOURCES.txt
enstop.egg-info/dependency_links.txt
enstop.egg-info/requires.txt
enstop.egg-info/top_level.txt
enstop.egg-info/zip-safe